learning_python_plus_rust/__init__.py
learning_python_plus_rust/cmd/__init__.py
learning_python_plus_rust/cmd/fib_numb.py
learning_python_plus_rust/fib_calcs/__init__.py
learning_python_plus_rust/fib_calcs/fib_number.py
learning_python_plus_rust/fib_calcs/fib_numbers.py
learning_python_plus_rust-0.0.1.dist-info/METADATA
learning_python_plus_rust-0.0.1.dist-info/WHEEL
learning_python_plus_rust-0.0.1.dist-info/entry_points.txt
learning_python_plus_rust-0.0.1.dist-info/top_level.txt
learning_python_plus_rust-0.0.1.dist-info/RECORD
